{
  "composition": {
    "section": "dynamic",
    "pathFrom": "../../assets/styles",
    "pathTo": "../../../../../../dist/junte-ui/lib/assets/styles",
    "from": [
      "chart/chart.scss"
    ],
    "to": "chart.scss"
  },
  "encapsuler": [
    {
      "host": "jnt-chart-host",
      "html": {
        "from": "chart.component.html",
        "to": "chart.encapsulated.html"
      },
      "scss": {
        "from": "chart.component.scss",
        "to": "../../assets/styles/dynamic/chart/chart.scss"
      }
    }
  ]
}
