{
  "composition": {
    "section": "shared",
    "pathFrom": "../../assets/styles",
    "pathTo": "../../../../../../dist/junte-ui/lib/assets/styles",
    "from": [
      "theme-switcher/_theme-switcher.scss"
    ],
    "to": "_theme-switcher.scss"
  },
  "encapsuler": [
    {
      "host": "jnt-theme-switcher-host",
      "html": {
        "from": "theme-switcher.component.html",
        "to": "theme-switcher.encapsulated.html"
      },
      "scss": {
        "from": "theme-switcher.component.scss",
        "to": "../../assets/styles/shared/theme-switcher/_theme-switcher.scss"
      }
    }
  ]
}
